setup.py
binrobot/BaseRobot.py
binrobot/EnvLoader.py
binrobot/KlineRobot.py
binrobot/__init__.py
binrobot.egg-info/PKG-INFO
binrobot.egg-info/SOURCES.txt
binrobot.egg-info/dependency_links.txt
binrobot.egg-info/not-zip-safe
binrobot.egg-info/requires.txt
binrobot.egg-info/top_level.txt