Metadata-Version: 1.0
Name: binrobot
Version: 0.1.0
Summary: Bin robot
Home-page: UNKNOWN
Author: cherepanov_max95
Author-email: cherepanov@ku66.ru
License: UNKNOWN
Platform: UNKNOWN
